turtle_language_server/__init__.py
turtle_language_server/entry.py
turtle_language_server/server.py
turtle_language_server-0.1.2.dist-info/entry_points.txt
turtle_language_server-0.1.2.dist-info/LICENSE
turtle_language_server-0.1.2.dist-info/WHEEL
turtle_language_server-0.1.2.dist-info/METADATA
turtle_language_server-0.1.2.dist-info/RECORD
