Metadata-Version: 2.1
Name: turtle-language-server
Version: 0.1.2
Summary: Language Server Protocol implementation for Turtle and RDF
Home-page: https://brickschema.org
License: BSD-3-Clause
Author: Gabe Fierro
Author-email: gtfierro@cs.berkeley.edu
Requires-Python: >=3.8,<4.0
Classifier: License :: OSI Approved :: BSD License
Classifier: Programming Language :: Python :: 3
Classifier: Programming Language :: Python :: 3.8
Classifier: Programming Language :: Python :: 3.9
Requires-Dist: pygls (>=0.9.1,<0.10.0)
Requires-Dist: rdflib (>=5.0.0,<6.0.0)
